hidp/__init__.py
hidp/apps.py
hidp/utils.py
hidp/accounts/__init__.py
hidp/accounts/account_management_urls.py
hidp/accounts/account_urls.py
hidp/accounts/apps.py
hidp/accounts/auth.py
hidp/accounts/email_change.py
hidp/accounts/email_verification.py
hidp/accounts/forms.py
hidp/accounts/mailers.py
hidp/accounts/models.py
hidp/accounts/password_validation.py
hidp/accounts/tokens.py
hidp/accounts/views.py
hidp/accounts/management/__init__.py
hidp/accounts/management/commands/__init__.py
hidp/accounts/management/commands/remove_complete_and_stale_email_change_requests.py
hidp/accounts/management/commands/remove_stale_unverified_accounts.py
hidp/accounts/migrations/0001_initial.py
hidp/accounts/migrations/__init__.py
hidp/api/__init__.py
hidp/api/apps.py
hidp/api/serializers.py
hidp/api/urls.py
hidp/api/views.py
hidp/compat/__init__.py
hidp/compat/uuid7.py
hidp/config/__init__.py
hidp/config/checks.py
hidp/config/oauth2_provider.py
hidp/config/oidc_clients.py
hidp/config/urls.py
hidp/csp/__init__.py
hidp/csp/decorators.py
hidp/csp/templatetags/__init__.py
hidp/csp/templatetags/csp_nonce.py
hidp/federated/__init__.py
hidp/federated/apps.py
hidp/federated/constants.py
hidp/federated/forms.py
hidp/federated/models.py
hidp/federated/oidc_client_urls.py
hidp/federated/oidc_management_urls.py
hidp/federated/tokens.py
hidp/federated/views.py
hidp/federated/auth/__init__.py
hidp/federated/auth/backends.py
hidp/federated/management/__init__.py
hidp/federated/management/commands/__init__.py
hidp/federated/management/commands/refresh_oidc_clients_jwks.py
hidp/federated/migrations/0001_initial.py
hidp/federated/migrations/0002_openidconnection_last_usage.py
hidp/federated/migrations/__init__.py
hidp/federated/oidc/__init__.py
hidp/federated/oidc/authorization_code_flow.py
hidp/federated/oidc/exceptions.py
hidp/federated/oidc/jwks.py
hidp/federated/providers/__init__.py
hidp/federated/providers/base.py
hidp/federated/providers/google.py
hidp/federated/providers/microsoft.py
django_hidp-1.6.0.dist-info/METADATA
django_hidp-1.6.0.dist-info/WHEEL
django_hidp-1.6.0.dist-info/top_level.txt
django_hidp-1.6.0.dist-info/RECORD
