Metadata-Version: 2.4
Name: django-hidp
Version: 1.6.0
Summary: Full-featured authentication system for Django projects
Author-email: Jaap Roes <jroes@leukeleu.nl>, Dennis Bunskoek <dbunskoek@leukeleu.nl>, Ramon de Jezus <rdejezus@leukeleu.nl>, Thomas Kalverda <tkalverda@leukeleu.nl>, Wouter de Vries <wdevries@leukeleu.nl>
License-Expression: BSD-3-Clause
Project-URL: Documentation, https://leukeleu.github.io/django-hidp/
Project-URL: Repository, https://github.com/leukeleu/django-hidp/
Project-URL: Issues, https://github.com/leukeleu/django-hidp/issues
Project-URL: Releasenotes, https://github.com/leukeleu/django-hidp/releases
Classifier: Development Status :: 5 - Production/Stable
Classifier: Framework :: Django
Classifier: Intended Audience :: Developers
Classifier: Programming Language :: Python :: 3
Requires-Python: >=3.11
Requires-Dist: Django<6,>=4.2
Requires-Dist: django-ratelimit<5,>=4.1.0
Requires-Dist: jwcrypto<2,>=1.5
Requires-Dist: requests<3,>=2.32
Provides-Extra: oidc-provider
Requires-Dist: django-oauth-toolkit<3.1,>=3.0.1; extra == "oidc-provider"
Requires-Dist: djangorestframework<3.16,>=3.15.2; extra == "oidc-provider"
Provides-Extra: otp
Requires-Dist: django-otp<2,>=1.5.0; extra == "otp"
Requires-Dist: segno<2,>=1.3.0; extra == "otp"
Provides-Extra: recommended
Requires-Dist: Django<6,>=4.2; extra == "recommended"
Requires-Dist: django-ratelimit<5,>=4.1.0; extra == "recommended"
Requires-Dist: jwcrypto<2,>=1.5; extra == "recommended"
Requires-Dist: requests<3,>=2.32; extra == "recommended"
Requires-Dist: django-otp<2,>=1.5.0; extra == "recommended"
Requires-Dist: segno<2,>=1.3.0; extra == "recommended"
Provides-Extra: all
Requires-Dist: Django<6,>=4.2; extra == "all"
Requires-Dist: django-ratelimit<5,>=4.1.0; extra == "all"
Requires-Dist: jwcrypto<2,>=1.5; extra == "all"
Requires-Dist: requests<3,>=2.32; extra == "all"
Requires-Dist: django-oauth-toolkit<3.1,>=3.0.1; extra == "all"
Requires-Dist: djangorestframework<3.16,>=3.15.2; extra == "all"
Requires-Dist: django-otp<2,>=1.5.0; extra == "all"
Requires-Dist: segno<2,>=1.3.0; extra == "all"
